{
  "elements": [
    {
      "label": "Main Panel",
      "position": [
        50.0,
        50.0
      ],
      "size": [
        300.0,
        150.0
      ],
      "type": "rectangle"
    },
    {
      "label": "Submit Button",
      "position": [
        200.0,
        300.0
      ],
      "size": [
        120.0,
        50.0
      ],
      "type": "button"
    },
    {
      "font_size": 16.0,
      "label": "Welcome Text",
      "position": [
        100.0,
        80.0
      ],
      "size": [
        180.0,
        20.0
      ],
      "type": "single-line-label"
    },
    {
      "label": "Progress Bar",
      "maxValue": 100,
      "minValue": 0,
      "position": [
        400.0,
        250.0
      ],
      "size": [
        400.0,
        30.0
      ],
      "type": "slider-int",
      "value": 60
    },
    {
      "label": "Logo Area",
      "position": [
        800.0,
        100.0
      ],
      "size": [
        250.0,
        150.0
      ],
      "type": "rectangle"
    }
  ],
  "name": "template2",
  "resolution": [
    1920.0,
    1011.0
  ]
}
